zipline_norgatedata/CHANGES.txt
zipline_norgatedata/LICENSE.txt
zipline_norgatedata/__init__.py
zipline_norgatedata/pipelines.py
zipline_norgatedata/version.py
zipline_norgatedata/zipline_norgatedata.py
zipline_norgatedata-3.1.2.dist-info/LICENSE.TXT
zipline_norgatedata-3.1.2.dist-info/METADATA
zipline_norgatedata-3.1.2.dist-info/WHEEL
zipline_norgatedata-3.1.2.dist-info/top_level.txt
zipline_norgatedata-3.1.2.dist-info/RECORD
