Metadata-Version: 2.1
Name: zipline-norgatedata
Version: 3.1.2
Summary: Zipline extension to provide bundles of data from Norgate Data into the Zipline algorithmic trading library for the Python programming language
Home-page: https://norgatedata.com
Author: NorgateData Pty Ltd
Author-email: support@norgatedata.com
License: EULA
Classifier: Intended Audience :: Financial and Insurance Industry
Classifier: Development Status :: 5 - Production/Stable
Classifier: Environment :: Win32 (MS Windows)
Classifier: Intended Audience :: Financial and Insurance Industry
Classifier: Programming Language :: Python :: 3.8
Classifier: Programming Language :: Python :: 3.9
Classifier: License :: Other/Proprietary License
Classifier: Operating System :: Microsoft :: Windows
Classifier: Topic :: Office/Business :: Financial :: Investment
Requires-Python: >=3.8
License-File: LICENSE.TXT
Requires-Dist: norgatedata
Requires-Dist: logbook
